cli/__init__.py
cli/__main__.py
cli/commands/__init__.py
cli/commands/competition.py
cli/commands/player.py
cli/commands/team.py
transfermarket/__init__.py
transfermarket/market.py
transfermarket/common/__init__.py
transfermarket/common/currency.py
transfermarket/common/gender.py
transfermarket/common/utils.py
transfermarket/models/__init__.py
transfermarket/models/club.py
transfermarket/models/competition.py
transfermarket/models/domain.py
transfermarket/models/meta.py
transfermarket/models/player.py
transfermarket/models/team.py
transfermarket/page/__init__.py
transfermarket/page/competitions.py
transfermarket/page/home.py
transfermarket/page/object.py
transfermarket/page/player.py
transfermarket/page/utils.py
transfermarket/services/__init__.py
transfermarket/services/currency.py
transfermarket/services/market.py
transfermarket-0.0.3.dist-info/LICENSE
transfermarket-0.0.3.dist-info/METADATA
transfermarket-0.0.3.dist-info/WHEEL
transfermarket-0.0.3.dist-info/entry_points.txt
transfermarket-0.0.3.dist-info/top_level.txt
transfermarket-0.0.3.dist-info/RECORD
