Metadata-Version: 2.1
Name: transfermarket
Version: 0.0.3
Summary: A python module for retrieving information from https://www.transfermarkt.com.
Author-email: Omar Crosby <omar.crosby@gmail.com>
Project-URL: Homepage, https://github.com/ocrosby/transfermarkt
Project-URL: Bug Tracker, https://github.com/ocrosby/transfermarkt/issues
Project-URL: Target URL, https://www.transfermarkt.com
Keywords: transfermarkt,football,soccer,football club,football player,football manager,football league,football competition,football transfer,football statistics,football data
Classifier: Programming Language :: Python :: 3
Classifier: License :: OSI Approved :: GNU General Public License (GPL)
Classifier: Operating System :: OS Independent
Requires-Python: >=3.8
License-File: LICENSE
